labcodes/__init__.py
labcodes/app/mat_editor.py
labcodes/calc/__init__.py
labcodes/calc/base.py
labcodes/calc/qubits.py
labcodes/calc/resonator_qc.py
labcodes/crosstalk.py
labcodes/enr_cross.py
labcodes/fileio/__init__.py
labcodes/fileio/base.py
labcodes/fileio/data_logger.py
labcodes/fileio/json.py
labcodes/fileio/labber.py
labcodes/fileio/labrad.py
labcodes/fileio/ltspice.py
labcodes/fit_resonator.py
labcodes/fitter.py
labcodes/frog/__init__.py
labcodes/frog/benchmark.py
labcodes/frog/iq_scatter.py
labcodes/frog/labrad_timefunc2freq.py
labcodes/frog/pulse_calc.py
labcodes/frog/routine.py
labcodes/frog/state_list.py
labcodes/frog/tele.py
labcodes/frog/tele_gate.py
labcodes/frog/tele_state.py
labcodes/frog/tele_swep.py
labcodes/misc.py
labcodes/models.py
labcodes/peak_find.py
labcodes/plotter/__init__.py
labcodes/plotter/mat.py
labcodes/plotter/matrix.py
labcodes/plotter/misc.py
labcodes/plotter/plot2d.py
labcodes/state_disc.py
labcodes/tomo.py
labcodes-1.0.4.dist-info/licenses/LICENSE
labcodes-1.0.4.dist-info/WHEEL
labcodes-1.0.4.dist-info/METADATA
labcodes-1.0.4.dist-info/RECORD
