Metadata-Version: 2.4
Name: labcodes
Version: 1.0.4
Summary: Simple routines for superconducting quantum circuits.
Author: Qiujv
Author-email: Qiujv <qiujv@outlook.com>
License-Expression: GPL-3.0-or-later
License-File: LICENSE
Classifier: Programming Language :: Python :: 3
Requires-Dist: numpy
Requires-Dist: scipy
Requires-Dist: matplotlib
Requires-Dist: pandas
Requires-Dist: lmfit>=0.9.5
Requires-Dist: tqdm
Requires-Dist: attrs
Requires-Dist: cvxpy
Requires-Dist: scikit-learn
Requires-Dist: json-tricks>=3.17.3
Requires-Dist: typing-extensions>=4.15.0
Requires-Dist: pyarrow>=21.0.0
Requires-Dist: h5py>=2.6
Requires-Python: >=3.10, <=3.13
Project-URL: Homepage, https://github.com/Qiujv/LabCodes
